<?xml version='1.0' encoding='utf-8'?>
<TextureAtlas imagePath="AdRumor.png">
<SubTexture name="AdRumor idle0000" x="153" y="1391" width="228" height="246" frameX="-176" frameY="-170" frameWidth="600" frameHeight="600" />
<SubTexture name="AdRumor idle0001" x="381" y="1391" width="228" height="246" frameX="-176" frameY="-171" frameWidth="600" frameHeight="600" />
<SubTexture name="AdRumor idle0002" x="609" y="1391" width="229" height="245" frameX="-176" frameY="-173" frameWidth="600" frameHeight="600" />
<SubTexture name="AdRumor idle0003" x="1293" y="1391" width="230" height="244" frameX="-175" frameY="-177" frameWidth="600" frameHeight="600" />
<SubTexture name="AdRumor idle0004" x="0" y="1639" width="232" height="243" frameX="-174" frameY="-182" frameWidth="600" frameHeight="600" />
<SubTexture name="AdRumor idle0005" x="930" y="1639" width="234" height="240" frameX="-173" frameY="-189" frameWidth="600" frameHeight="600" />
<SubTexture name="AdRumor idle0006" x="232" y="1639" width="235" height="243" frameX="-172" frameY="-191" frameWidth="600" frameHeight="600" />
<SubTexture name="AdRumor idle0007" x="1164" y="1639" width="234" height="240" frameX="-173" frameY="-194" frameWidth="600" frameHeight="600" />
<SubTexture name="AdRumor idle0008" x="698" y="1639" width="232" height="242" frameX="-174" frameY="-192" frameWidth="600" frameHeight="600" />
<SubTexture name="AdRumor idle0009" x="467" y="1639" width="231" height="243" frameX="-175" frameY="-190" frameWidth="600" frameHeight="600" />
<SubTexture name="AdRumor idle0010" x="1723" y="0" width="230" height="244" frameX="-175" frameY="-189" frameWidth="600" frameHeight="600" />
<SubTexture name="AdRumor idle0011" x="838" y="1391" width="228" height="245" frameX="-176" frameY="-186" frameWidth="600" frameHeight="600" />
<SubTexture name="AdRumor idle0012" x="1066" y="1391" width="227" height="245" frameX="-177" frameY="-182" frameWidth="600" frameHeight="600" />
<SubTexture name="AdRumor idle0013" x="153" y="1391" width="228" height="246" frameX="-176" frameY="-170" frameWidth="600" frameHeight="600" />
<SubTexture name="AdRumor up0000" x="500" y="1139" width="154" height="251" frameX="-207" frameY="-169" frameWidth="600" frameHeight="600" />
<SubTexture name="AdRumor up0001" x="654" y="1139" width="154" height="251" frameX="-210" frameY="-169" frameWidth="600" frameHeight="600" />
<SubTexture name="AdRumor up0002" x="0" y="1391" width="153" height="248" frameX="-213" frameY="-172" frameWidth="600" frameHeight="600" />
<SubTexture name="AdRumor up0003" x="1572" y="0" width="151" height="250" frameX="-215" frameY="-169" frameWidth="600" frameHeight="600" />
<SubTexture name="AdRumor up0004" x="808" y="1139" width="150" height="251" frameX="-216" frameY="-169" frameWidth="600" frameHeight="600" />
<SubTexture name="AdRumor up0005" x="958" y="1139" width="149" height="251" frameX="-217" frameY="-169" frameWidth="600" frameHeight="600" />
<SubTexture name="AdRumor up0006" x="1107" y="1139" width="149" height="251" frameX="-217" frameY="-169" frameWidth="600" frameHeight="600" />
<SubTexture name="AdRumor up0007" x="1256" y="1139" width="149" height="251" frameX="-217" frameY="-169" frameWidth="600" frameHeight="600" />
<SubTexture name="AdRumor up0008" x="1422" y="0" width="150" height="251" frameX="-216" frameY="-169" frameWidth="600" frameHeight="600" />
<SubTexture name="AdRumor up0009" x="1572" y="250" width="150" height="250" frameX="-216" frameY="-169" frameWidth="600" frameHeight="600" />
<SubTexture name="AdRumor up0010" x="1572" y="500" width="150" height="250" frameX="-216" frameY="-169" frameWidth="600" frameHeight="600" />
<SubTexture name="AdRumor left0000" x="1071" y="519" width="173" height="258" frameX="-209" frameY="-164" frameWidth="600" frameHeight="600" />
<SubTexture name="AdRumor left0001" x="0" y="881" width="145" height="258" frameX="-232" frameY="-164" frameWidth="600" frameHeight="600" />
<SubTexture name="AdRumor left0002" x="145" y="881" width="165" height="258" frameX="-234" frameY="-164" frameWidth="600" frameHeight="600" />
<SubTexture name="AdRumor left0003" x="310" y="881" width="180" height="258" frameX="-232" frameY="-164" frameWidth="600" frameHeight="600" />
<SubTexture name="AdRumor left0004" x="1071" y="260" width="186" height="259" frameX="-221" frameY="-163" frameWidth="600" frameHeight="600" />
<SubTexture name="AdRumor left0005" x="383" y="620" width="189" height="260" frameX="-195" frameY="-163" frameWidth="600" frameHeight="600" />
<SubTexture name="AdRumor left0006" x="0" y="620" width="187" height="261" frameX="-170" frameY="-164" frameWidth="600" frameHeight="600" />
<SubTexture name="AdRumor left0007" x="572" y="620" width="189" height="260" frameX="-157" frameY="-165" frameWidth="600" frameHeight="600" />
<SubTexture name="AdRumor left0008" x="882" y="0" width="189" height="260" frameX="-156" frameY="-165" frameWidth="600" frameHeight="600" />
<SubTexture name="AdRumor left0009" x="882" y="260" width="187" height="260" frameX="-161" frameY="-165" frameWidth="600" frameHeight="600" />
<SubTexture name="AdRumor left0010" x="882" y="520" width="186" height="260" frameX="-164" frameY="-165" frameWidth="600" frameHeight="600" />
<SubTexture name="AdRumor down0000" x="1723" y="244" width="195" height="234" frameX="-211" frameY="-181" frameWidth="600" frameHeight="600" />
<SubTexture name="AdRumor down0001" x="0" y="1139" width="197" height="252" frameX="-216" frameY="-175" frameWidth="600" frameHeight="600" />
<SubTexture name="AdRumor down0002" x="187" y="620" width="196" height="261" frameX="-222" frameY="-173" frameWidth="600" frameHeight="600" />
<SubTexture name="AdRumor down0003" x="680" y="285" width="196" height="271" frameX="-226" frameY="-168" frameWidth="600" frameHeight="600" />
<SubTexture name="AdRumor down0004" x="680" y="0" width="202" height="285" frameX="-225" frameY="-157" frameWidth="600" frameHeight="600" />
<SubTexture name="AdRumor down0005" x="451" y="312" width="213" height="301" frameX="-221" frameY="-142" frameWidth="600" frameHeight="600" />
<SubTexture name="AdRumor down0006" x="0" y="0" width="224" height="312" frameX="-216" frameY="-131" frameWidth="600" frameHeight="600" />
<SubTexture name="AdRumor down0007" x="224" y="0" width="228" height="312" frameX="-214" frameY="-131" frameWidth="600" frameHeight="600" />
<SubTexture name="AdRumor down0008" x="452" y="0" width="228" height="310" frameX="-213" frameY="-132" frameWidth="600" frameHeight="600" />
<SubTexture name="AdRumor down0009" x="0" y="312" width="226" height="308" frameX="-213" frameY="-133" frameWidth="600" frameHeight="600" />
<SubTexture name="AdRumor down0010" x="226" y="312" width="225" height="308" frameX="-213" frameY="-133" frameWidth="600" frameHeight="600" />
<SubTexture name="AdRumor right0000" x="1071" y="0" width="199" height="260" frameX="-162" frameY="-162" frameWidth="600" frameHeight="600" />
<SubTexture name="AdRumor right0001" x="490" y="881" width="182" height="256" frameX="-196" frameY="-165" frameWidth="600" frameHeight="600" />
<SubTexture name="AdRumor right0002" x="672" y="881" width="159" height="256" frameX="-215" frameY="-165" frameWidth="600" frameHeight="600" />
<SubTexture name="AdRumor right0003" x="831" y="881" width="147" height="255" frameX="-218" frameY="-166" frameWidth="600" frameHeight="600" />
<SubTexture name="AdRumor right0004" x="978" y="881" width="149" height="253" frameX="-219" frameY="-167" frameWidth="600" frameHeight="600" />
<SubTexture name="AdRumor right0005" x="197" y="1139" width="151" height="252" frameX="-220" frameY="-168" frameWidth="600" frameHeight="600" />
<SubTexture name="AdRumor right0006" x="348" y="1139" width="152" height="252" frameX="-220" frameY="-168" frameWidth="600" frameHeight="600" />
<SubTexture name="AdRumor right0007" x="1270" y="0" width="152" height="253" frameX="-219" frameY="-167" frameWidth="600" frameHeight="600" />
<SubTexture name="AdRumor right0008" x="1270" y="253" width="151" height="253" frameX="-219" frameY="-167" frameWidth="600" frameHeight="600" />
<SubTexture name="AdRumor right0009" x="1270" y="506" width="149" height="253" frameX="-219" frameY="-167" frameWidth="600" frameHeight="600" />
<SubTexture name="AdRumor right0010" x="1270" y="759" width="148" height="253" frameX="-219" frameY="-167" frameWidth="600" frameHeight="600" />
</TextureAtlas>
